pytorch_revgrad/__init__.py
pytorch_revgrad/functional.py
pytorch_revgrad/module.py
pytorch_revgrad/version.py
pytorch_revgrad-0.2.0.dist-info/LICENSE
pytorch_revgrad-0.2.0.dist-info/LICENSE.md
pytorch_revgrad-0.2.0.dist-info/WHEEL
pytorch_revgrad-0.2.0.dist-info/METADATA
pytorch_revgrad-0.2.0.dist-info/RECORD
